Metadata-Version: 2.1
Name: blandai
Version: 0.1.1
Summary: A Python wrapper for the Bland.ai API
Home-page: https://github.com/lankabelgezogen/blandailibrary
Author: LanKabelGezogen
Author-email: cybertom1234@gmail.com
License: MIT
Keywords: blandai API wrapper
Platform: UNKNOWN
